awil_ad9833/__init__.py
awil_ad9833/awil_ad9833.py
awil_ad9833-0.1.0.dist-info/LICENSE
awil_ad9833-0.1.0.dist-info/METADATA
awil_ad9833-0.1.0.dist-info/WHEEL
awil_ad9833-0.1.0.dist-info/top_level.txt
awil_ad9833-0.1.0.dist-info/RECORD
