Metadata-Version: 2.1
Name: awil_ad9833
Version: 0.1.0
Author: Noriki Mochizuki
Author-email: noriki.mochizuki.mj@gmail.com
License: MIT
License-File: LICENSE
Requires-Dist: awil-ft232h
